unito.py
Unito-1.0.0.dist-info/LICENSE
Unito-1.0.0.dist-info/METADATA
Unito-1.0.0.dist-info/WHEEL
Unito-1.0.0.dist-info/top_level.txt
Unito-1.0.0.dist-info/RECORD
